mcfine/__init__.py
mcfine/fitting.py
mcfine/line_info.py
mcfine/plotting.py
mcfine/utils.py
mcfine/toml/config_defaults.toml
mcfine/toml/local_defaults.toml
mcfine-0.3.dist-info/licenses/LICENSE
mcfine-0.3.dist-info/METADATA
mcfine-0.3.dist-info/WHEEL
mcfine-0.3.dist-info/top_level.txt
mcfine-0.3.dist-info/RECORD
