Metadata-Version: 2.4
Name: mcfine
Version: 0.3
Summary: Monte-Carlo, Multi-Component ISM Fitting
Author-email: "Thomas G. Williams" <thomas.williams-4@manchester.ac.uk>, "Elizabeth J. Watkins" <elizabeth.watkins@manchester.ac.uk>
Maintainer-email: "Thomas G. Williams" <thomas.williams-4@manchester.ac.uk>
License:                     GNU GENERAL PUBLIC LICENSE
Project-URL: Homepage, https://mcfine.readthedocs.io
Project-URL: Bug Reports, https://github.com/thomaswilliamsastro/issues
Project-URL: Source, https://github.com/thomaswilliamsastro/mcfine
Classifier: Development Status :: 3 - Alpha
Classifier: License :: OSI Approved :: GNU General Public License v3 or later (GPLv3+)
Classifier: Programming Language :: Python :: 3.11
Classifier: Programming Language :: Python :: 3.12
Requires-Python: >=3.11
License-File: LICENSE
Requires-Dist: astropy==7.1.0
Requires-Dist: corner==2.2.3
Requires-Dist: emcee==3.1.6
Requires-Dist: lmfit==1.3.4
Requires-Dist: matplotlib==3.10.6
Requires-Dist: numdifftools==0.9.41
Requires-Dist: numpy==2.3.3
Requires-Dist: scipy==1.16.2
Requires-Dist: specutils==2.1.0
Requires-Dist: threadpoolctl==3.6.0
Requires-Dist: tqdm==4.67.1
Provides-Extra: rt
Requires-Dist: ndradex==0.3.1; extra == "rt"
Provides-Extra: docs
Requires-Dist: sphinx-automodapi; extra == "docs"
Requires-Dist: sphinx-rtd-theme; extra == "docs"
Dynamic: license-file
